academic_emotion/__init__.py
academic_emotion/demo_emotion_main_speaker.py
academic_emotion/face_models.py
academic_emotion-0.1.2.dist-info/licenses/LICENSE
academic_emotion-0.1.2.dist-info/METADATA
academic_emotion-0.1.2.dist-info/WHEEL
academic_emotion-0.1.2.dist-info/top_level.txt
academic_emotion-0.1.2.dist-info/RECORD
